microserver/__init__.py
microserver/http_server.py
microserver/request_handler.py
microserver/response.py
microserver/route.py
microserver/server.py
BLM16_MicroServer-1.0.0.dist-info/LICENSE
BLM16_MicroServer-1.0.0.dist-info/METADATA
BLM16_MicroServer-1.0.0.dist-info/WHEEL
BLM16_MicroServer-1.0.0.dist-info/top_level.txt
BLM16_MicroServer-1.0.0.dist-info/RECORD
