Metadata-Version: 2.1
Name: BLM16-MicroServer
Version: 1.0.0
Summary: A lightweight and flexible webserver.
Author-email: BLM16 <myers.bradley@hotmail.com>
License: MIT License
Project-URL: Repository, https://github.com/BLM16/MicroServer.git
Project-URL: Issues, https://github.com/BLM16/MicroServer/issues
Project-URL: Changelog, https://github.com/BLM16/MicroServer/blob/master/CHANGELOG.md
Keywords: microserver,webserver,lightweight
Classifier: License :: OSI Approved :: MIT License
Classifier: Environment :: Web Environment
Classifier: Intended Audience :: Developers
Classifier: Topic :: Internet
Classifier: Topic :: Internet :: WWW/HTTP
Classifier: Topic :: Internet :: WWW/HTTP :: HTTP Servers
Classifier: Topic :: Internet :: WWW/HTTP :: WSGI
Classifier: Topic :: Internet :: WWW/HTTP :: WSGI :: Server
Classifier: Programming Language :: Python :: 3
Requires-Python: >=3
License-File: LICENSE
